shellwrap/__init__.py
shellwrap/shellwrap.py
shellwrap/utils.py
shellwrap-0.1.0.data/data/LICENSE.txt
shellwrap-0.1.0.dist-info/METADATA
shellwrap-0.1.0.dist-info/RECORD
shellwrap-0.1.0.dist-info/WHEEL
shellwrap-0.1.0.dist-info/top_level.txt
