Metadata-Version: 2.1
Name: shellwrap
Version: 0.1.0
Summary: Python and shell scripts interaction library
Home-page: https://gitlab.com/licorna/shellwrap
Author: Rodrigo Valin
Author-email: licorna@gmail.com
License: UNKNOWN
Platform: UNKNOWN
